sc_sme_analysis/__init__.py
sc_sme_analysis/main.py
sc_sme_analysis/utils.py
sc_sme_analysis/analyzer/__init__.py
sc_sme_analysis/analyzer/inclusive_finance_balance_analyzer.py
sc_sme_analysis/analyzer/valid_clearing_account_analyzer.py
sc_sme_analysis/analyzer/valid_credit_account_analyzer.py
sc_sme_analysis/configs/__init__.py
sc_sme_analysis/configs/default.py
sc_sme_analysis/summary/__init__.py
sc_sme_analysis/summary/branch_summary_analyzer.py
sc_sme_analysis/summary/manager_summary_analyzer.py
sc_sme_analysis/tests/__init__.py
sc_sme_analysis/tests/sample_config/production.yml
sc_sme_analysis-0.0.6.dist-info/LICENSE
sc_sme_analysis-0.0.6.dist-info/METADATA
sc_sme_analysis-0.0.6.dist-info/WHEEL
sc_sme_analysis-0.0.6.dist-info/entry_points.txt
sc_sme_analysis-0.0.6.dist-info/top_level.txt
sc_sme_analysis-0.0.6.dist-info/RECORD
